{"code":"0176P0","name":"FOCUS AI반도체위클리고정커버드콜","updated":"2026-04-22T18:17:41+09:00","data":[{"date":"2026-04-07","open":9985,"high":9985,"low":9670,"close":9845,"volume":41540,"ma5":null,"ma20":null,"ma60":null,"macd":0.0,"macd_signal":0.0,"macd_hist":0.0,"rsi":null,"obv":0.0,"vwap":9833.333333333334,"mfi":null,"bb_upper":null,"bb_mid":null,"bb_lower":null},{"date":"2026-04-08","open":10695,"high":10730,"low":10370,"close":10730,"volume":32776,"ma5":null,"ma20":null,"ma60":null,"macd":70.59829059829099,"macd_signal":14.119658119658197,"macd_hist":56.47863247863279,"rsi":null,"obv":32776.0,"vwap":10175.870965426917,"mfi":null,"bb_upper":null,"bb_mid":null,"bb_lower":null},{"date":"2026-04-09","open":10685,"high":10695,"low":10410,"close":10570,"volume":60102,"ma5":null,"ma20":null,"ma60":null,"macd":112.34226994910568,"macd_signal":33.7641804855477,"macd_hist":78.57808946355799,"rsi":null,"obv":-27326.0,"vwap":10346.88045251876,"mfi":null,"bb_upper":null,"bb_mid":null,"bb_lower":null},{"date":"2026-04-10","open":10725,"high":10910,"low":10725,"close":10725,"volume":29465,"ma5":null,"ma20":null,"ma60":null,"macd":156.13208545246198,"macd_signal":58.23776147893056,"macd_hist":97.89432397353141,"rsi":null,"obv":2139.0,"vwap":10425.950891794757,"mfi":null,"bb_upper":null,"bb_mid":null,"bb_lower":null},{"date":"2026-04-13","open":10595,"high":10805,"low":10505,"close":10665,"volume":19912,"ma5":10507.0,"ma20":null,"ma60":null,"macd":183.87473765079085,"macd_signal":83.36515671330262,"macd_hist":100.50958093748822,"rsi":null,"obv":-17773.0,"vwap":10451.12676260689,"mfi":null,"bb_upper":null,"bb_mid":null,"bb_lower":null},{"date":"2026-04-14","open":11180,"high":11180,"low":10930,"close":10930,"volume":10186,"ma5":10724.0,"ma20":null,"ma60":null,"macd":224.65459635146544,"macd_signal":111.62304464093519,"macd_hist":113.03155171053025,"rsi":null,"obv":-7587.0,"vwap":10480.648396836115,"mfi":null,"bb_upper":null,"bb_mid":null,"bb_lower":null},{"date":"2026-04-15","open":11295,"high":11362,"low":11110,"close":11235,"volume":36622,"ma5":10825.0,"ma20":null,"ma60":null,"macd":278.37494608730594,"macd_signal":144.97342493020935,"macd_hist":133.4015211570966,"rsi":null,"obv":29035.0,"vwap":10600.552643865574,"mfi":null,"bb_upper":null,"bb_mid":null,"bb_lower":null},{"date":"2026-04-16","open":11220,"high":11485,"low":11160,"close":11485,"volume":20513,"ma5":11008.0,"ma20":null,"ma60":null,"macd":337.23419507023027,"macd_signal":183.42557895821355,"macd_hist":153.80861611201672,"rsi":null,"obv":49548.0,"vwap":10663.951339885418,"mfi":null,"bb_upper":null,"bb_mid":null,"bb_lower":null},{"date":"2026-04-17","open":11590,"high":11590,"low":11380,"close":11500,"volume":15998,"ma5":11163.0,"ma20":null,"ma60":null,"macd":380.7024477483592,"macd_signal":222.8809527162427,"macd_hist":157.8214950321165,"rsi":null,"obv":65546.0,"vwap":10713.425071941818,"mfi":null,"bb_upper":null,"bb_mid":null,"bb_lower":null},{"date":"2026-04-20","open":11565,"high":11600,"low":11395,"close":11520,"volume":17229,"ma5":11334.0,"ma20":null,"ma60":null,"macd":412.0157232340898,"macd_signal":260.70790681981214,"macd_hist":151.30781641427768,"rsi":null,"obv":82775.0,"vwap":10761.388427591559,"mfi":null,"bb_upper":null,"bb_mid":null,"bb_lower":null},{"date":"2026-04-21","open":11555,"high":11910,"low":11555,"close":11910,"volume":19927,"ma5":11530.0,"ma20":null,"ma60":null,"macd":462.96469151226665,"macd_signal":301.15926375830304,"macd_hist":161.8054277539636,"rsi":null,"obv":102702.0,"vwap":10828.862560664322,"mfi":null,"bb_upper":null,"bb_mid":null,"bb_lower":null},{"date":"2026-04-22","open":12000,"high":12090,"low":11775,"close":12090,"volume":15820,"ma5":11701.0,"ma20":null,"ma60":null,"macd":511.96499780984595,"macd_signal":343.32041056861163,"macd_hist":168.64458724123432,"rsi":null,"obv":118522.0,"vwap":10886.003034563195,"mfi":null,"bb_upper":null,"bb_mid":null,"bb_lower":null}],"dataW":[{"date":"2026-04-10","open":9985,"high":10910,"low":9670,"close":10725,"volume":163883,"ma5":null,"ma20":null,"ma60":null,"macd":0.0,"macd_signal":0.0,"macd_hist":0.0,"rsi":null,"obv":0.0,"vwap":10435.0,"mfi":null,"bb_upper":null,"bb_mid":null,"bb_lower":null},{"date":"2026-04-17","open":10595,"high":11590,"low":10505,"close":11500,"volume":103231,"ma5":null,"ma20":null,"ma60":null,"macd":61.823361823362575,"macd_signal":12.364672364672515,"macd_hist":49.45868945869006,"rsi":null,"obv":103231.0,"vwap":10730.003868510574,"mfi":null,"bb_upper":null,"bb_mid":null,"bb_lower":null},{"date":"2026-04-24","open":11565,"high":12090,"low":11395,"close":12090,"volume":52976,"ma5":null,"ma20":null,"ma60":null,"macd":156.62145599467658,"macd_signal":41.21602909067333,"macd_hist":115.40542690400325,"rsi":null,"obv":156207.0,"vwap":10916.746290105908,"mfi":null,"bb_upper":null,"bb_mid":null,"bb_lower":null}],"dataM":[{"date":"2026-04-30","open":9985,"high":12090,"low":9670,"close":12090,"volume":320090,"ma5":null,"ma20":null,"ma60":null,"macd":0.0,"macd_signal":0.0,"macd_hist":0.0,"rsi":null,"obv":0.0,"vwap":11283.333333333334,"mfi":null,"bb_upper":null,"bb_mid":null,"bb_lower":null}],"investor":{"data":[{"date":"2026-04-07","inst":-12501,"foreign":0,"retail":12501,"foreign_ratio":0.0},{"date":"2026-04-08","inst":-6908,"foreign":0,"retail":6908,"foreign_ratio":0.0},{"date":"2026-04-09","inst":-24050,"foreign":0,"retail":24050,"foreign_ratio":0.0},{"date":"2026-04-10","inst":1867,"foreign":457,"retail":-2324,"foreign_ratio":0.05},{"date":"2026-04-13","inst":8597,"foreign":185,"retail":-8782,"foreign_ratio":0.07},{"date":"2026-04-14","inst":-6134,"foreign":-642,"retail":6776,"foreign_ratio":0.0},{"date":"2026-04-15","inst":-9252,"foreign":0,"retail":9252,"foreign_ratio":0.0},{"date":"2026-04-16","inst":-3092,"foreign":0,"retail":3092,"foreign_ratio":0.0},{"date":"2026-04-17","inst":-5619,"foreign":0,"retail":5619,"foreign_ratio":0.0},{"date":"2026-04-20","inst":-4755,"foreign":0,"retail":4755,"foreign_ratio":0.0},{"date":"2026-04-21","inst":-9898,"foreign":0,"retail":9898,"foreign_ratio":0.0}],"cumulative":{"inst":{"total":-71745,"cumulative":[-12501,-19409,-43459,-41592,-32995,-39129,-48381,-51473,-57092,-61847,-71745]},"retail":{"total":71745,"cumulative":[12501,19409,43459,41135,32353,39129,48381,51473,57092,61847,71745]},"foreign":{"total":0,"cumulative":[0,0,0,457,642,0,0,0,0,0,0]}},"_source":"naver"},"meta":{"company":{"homepage":"http://${ URL }","nameKor":"${ CMP_KOR }"},"name":"FOCUS AI반도체위클리고정커버드콜","market":"KOSPI","price":"12,090","change":"180","changeRate":"1.51","changeDir":"RISING","volume":"15,820","marketCap":"109"}}